setup.py
MesaHandler/MesaAccess.py
MesaHandler/__init__.py
MesaHandler/MesaFileHandler/MesaEnvironmentHandler.py
MesaHandler/MesaFileHandler/MesaFileAccess.py
MesaHandler/MesaFileHandler/MesaFileInterface.py
MesaHandler/MesaFileHandler/__init__.py
MesaHandler/py_mesa_reader/__init__.py
MesaHandler/py_mesa_reader/setup.py
MesaHandler/py_mesa_reader/mesa_reader/MesaData.py
MesaHandler/py_mesa_reader/mesa_reader/MesaLogDir.py
MesaHandler/py_mesa_reader/mesa_reader/MesaProfileIndex.py
MesaHandler/py_mesa_reader/mesa_reader/__init__.py
MesaHandler/py_mesa_reader/mesa_reader/exceptions.py
MesaHandler/support/__init__.py
MesaHandler/support/definitions.py
MesaHandler/support/regex_def.py
MesaHandler/support/supportFunctions.py
PyMesaHandler.egg-info/PKG-INFO
PyMesaHandler.egg-info/SOURCES.txt
PyMesaHandler.egg-info/dependency_links.txt
PyMesaHandler.egg-info/top_level.txt
tests/__init__.py
tests/test_MesaFileAccess.py