Metadata-Version: 1.0
Name: PyMesaHandler
Version: 0.2.1
Summary: An easy way to handle Mesa using Python
Home-page: https://github.com/muma7490/PyMesaHandler
Author: Marco Müllner
Author-email: muellnermarco@gmail.com
License: MIT
Platform: UNKNOWN
